{
    "Striped Marlin": {
        "rarity": "Legendary"
    },
    "Vanta Ray": {
        "rarity": "Legendary"
    },
    "Dragon Fish": {
        "rarity": "Legendary"
    },
    "Antarctic Icefish": {
        "rarity": "Legendary"
    },
    "Goblin Shark": {
        "rarity": "Legendary"
    },
    "Skull Moray Eel": {
        "rarity": "Legendary"
    },
    "Angel Shark": {
        "rarity": "Legendary"
    },
    "Sharko": {
        "rarity": "Legendary"
    },
    "Umbrella Octopus": {
        "rarity": "Legendary"
    },
    "Ripsaw Catfish": {
        "rarity": "Legendary"
    },
    "Clione": {
        "rarity": "Legendary"
    },
    "Starfish": {
        "rarity": "Legendary"
    },
    "Skull Mackerel": {
        "rarity": "Rare"
    },
    "Barreleye": {
        "rarity": "Rare"
    },
    "Marlin": {
        "rarity": "Rare"
    },
    "Freshwater Angelfish": {
        "rarity": "Rare"
    },
    "Spiraldrift": {
        "rarity": "Rare"
    },
    "Sailfish": {
        "rarity": "Rare"
    },
    "Saw Shark": {
        "rarity": "Rare"
    },
    "Sunfish": {
        "rarity": "Rare"
    },
    "Spinepuff": {
        "rarity": "Rare"
    },
    "Betta": {
        "rarity": "Rare"
    },
    "Magma Discus": {
        "rarity": "Rare"
    },
    "Pelican Eel": {
        "rarity": "Rare"
    },
    "Crabbie": {
        "rarity": "Uncommon"
    },
    "Wahoo": {
        "rarity": "Uncommon"
    },
    "Skull Seahorse": {
        "rarity": "Uncommon"
    },
    "Hand Fish": {
        "rarity": "Uncommon"
    },
    "Turtlo": {
        "rarity": "Uncommon"
    },
    "Ocean Sunfish Fry": {
        "rarity": "Uncommon"
    },
    "Obsidian Tiger Oscar": {
        "rarity": "Uncommon"
    },
    "Duskray": {
        "rarity": "Uncommon"
    },
    "Bluefin Tuna": {
        "rarity": "Uncommon"
    },
    "Bluetang": {
        "rarity": "Uncommon"
    },
    "Squibby": {
        "rarity": "Uncommon"
    },
    "Octo": {
        "rarity": "Uncommon"
    },
    "Tripod Fish": {
        "rarity": "Uncommon"
    },
    "Moonfish": {
        "rarity": "Uncommon"
    },
    "Gwrasse": {
        "rarity": "Uncommon"
    },
    "Monk Fish": {
        "rarity": "Uncommon"
    },
    "Marine Angelfish": {
        "rarity": "Uncommon"
    },
    "Wolf Eel": {
        "rarity": "Common"
    },
    "Ghost Shark": {
        "rarity": "Common"
    },
    "Stonefish": {
        "rarity": "Common"
    },
    "Skull Piranha": {
        "rarity": "Common"
    },
    "Rosefin": {
        "rarity": "Common"
    },
    "Flying Fish": {
        "rarity": "Common"
    },
    "Zebream": {
        "rarity": "Common"
    },
    "Tunavax": {
        "rarity": "Common"
    },
    "Shrimprite": {
        "rarity": "Common"
    },
    "Silverfin": {
        "rarity": "Common"
    },
    "Emberfin": {
        "rarity": "Common"
    },
    "Coelancanth": {
        "rarity": "Common"
    },
    "PLACEHOLDER 5": {
        "rarity": "Common"
    },
    "Flounder": {
        "rarity": "Common"
    },
    "Piranha": {
        "rarity": "Common"
    },
    "Old Boot": {
        "rarity": "Trash"
    },
    "Tire": {
        "rarity": "Trash"
    },
    "Rusty Can": {
        "rarity": "Trash"
    }
}
